vixlib/__init__.py
vixlib/vegetationindex.py
remotesensing-0.0.1.dist-info/LICENSE.txt
remotesensing-0.0.1.dist-info/METADATA
remotesensing-0.0.1.dist-info/WHEEL
remotesensing-0.0.1.dist-info/top_level.txt
remotesensing-0.0.1.dist-info/RECORD
