Metadata-Version: 2.1
Name: remotesensing
Version: 0.0.1
Summary: remotesensing is a powerful Python library designed for calculating and analyzing vegetation indices from remote sensing and spectral data.
Author: Radhwane Derraz
Author-email: derrazradhwane@gmail.com
Classifier: Programming Language :: Python :: 3
Classifier: License :: OSI Approved :: Apache Software License
Classifier: Operating System :: OS Independent
Requires-Python: >=3.6
License-File: LICENSE.txt
